devtools_sql_escape/__init__.py
devtools_sql_escape-1.0.1.dist-info/METADATA
devtools_sql_escape-1.0.1.dist-info/WHEEL
devtools_sql_escape-1.0.1.dist-info/top_level.txt
devtools_sql_escape-1.0.1.dist-info/RECORD
